CHANGES
LICENSE
MANIFEST.in
README.rst
setup.py
xmlrpclibex/__init__.py
xmlrpclibex/xmlrpclibex.py
xmlrpclibex.egg-info/PKG-INFO
xmlrpclibex.egg-info/SOURCES.txt
xmlrpclibex.egg-info/dependency_links.txt
xmlrpclibex.egg-info/requires.txt
xmlrpclibex.egg-info/top_level.txt